glchat_python/__init__.py
glchat_python/client.py
glchat_python/message.py
glchat_python/models.py
glchat_python/py.typed
glchat_python-0.0.1b3.dist-info/METADATA
glchat_python-0.0.1b3.dist-info/WHEEL
glchat_python-0.0.1b3.dist-info/RECORD
