Metadata-Version: 2.4
Name: glchat-python
Version: 0.0.1b3
Summary: GLChat Python Client
Author-email: vincentchuardi <91732545+vincentchuardi@users.noreply.github.com>
Requires-Python: >=3.11
Requires-Dist: httpx>=0.28.1
Requires-Dist: pydantic>=2.0.0
